doorbw_test/__init__.py
doorbw_test/test.py
doorbw_test-0.1.dist-info/METADATA
doorbw_test-0.1.dist-info/WHEEL
doorbw_test-0.1.dist-info/top_level.txt
doorbw_test-0.1.dist-info/RECORD
