Metadata-Version: 2.1
Name: doorbw-test
Version: 0.1
Summary: for explain about pypi deploy
Home-page: https://github.com/doorBW/pypi_deploy_test
Author: beomwoo.moon
Author-email: doorbw@outlook.com
License: UNKNOWN
Download-URL: https://github.com/doorBW/pypi_deploy_test/archive/master.zip
Keywords: pypi deploy
Platform: UNKNOWN
Classifier: Programming Language :: Python :: 3
Classifier: Programming Language :: Python :: 3.2
Classifier: Programming Language :: Python :: 3.3
Classifier: Programming Language :: Python :: 3.4
Classifier: Programming Language :: Python :: 3.5
Classifier: Programming Language :: Python :: 3.6
Classifier: Programming Language :: Python :: 3.7
Requires-Python: >=3
